[
  {
    "full_name": "chonkie-inc/chonkie",
    "stargazers_count": 1048,
    "open_issues_count": 48,
    "forks_count": 62
  },
  {
    "full_name": "tindy2013/subconverter",
    "stargazers_count": 14509,
    "open_issues_count": 228,
    "forks_count": 3103
  },
  {
    "full_name": "zellij-org/zellij",
    "stargazers_count": 24461,
    "open_issues_count": 1248,
    "forks_count": 747
  },
  {
    "full_name": "go-resty/resty",
    "stargazers_count": 10921,
    "open_issues_count": 29,
    "forks_count": 751
  },
  {
    "full_name": "jd/tenacity",
    "stargazers_count": 7483,
    "open_issues_count": 123,
    "forks_count": 295
  },
  {
    "full_name": "litl/backoff",
    "stargazers_count": 2671,
    "open_issues_count": 64,
    "forks_count": 152
  },
  {
    "full_name": "grafana/k6",
    "stargazers_count": 27944,
    "open_issues_count": 775,
    "forks_count": 1370
  },
  {
    "full_name": "gohugoio/hugo",
    "stargazers_count": 81363,
    "open_issues_count": 473,
    "forks_count": 7875
  },
  {
    "full_name": "go-playground/validator",
    "stargazers_count": 18427,
    "open_issues_count": 325,
    "forks_count": 1372
  },
  {
    "full_name": "external-secrets/external-secrets",
    "stargazers_count": 5067,
    "open_issues_count": 194,
    "forks_count": 967
  },
  {
    "full_name": "mermaid-js/mermaid",
    "stargazers_count": 80062,
    "open_issues_count": 1361,
    "forks_count": 7623
  },
  {
    "full_name": "libjpeg-turbo/libjpeg-turbo",
    "stargazers_count": 3953,
    "open_issues_count": 20,
    "forks_count": 1070
  },
  {
    "full_name": "valeriansaliou/sonic",
    "stargazers_count": 20770,
    "open_issues_count": 73,
    "forks_count": 600
  },
  {
    "full_name": "cvilsmeier/go-sqlite-bench",
    "stargazers_count": 412,
    "open_issues_count": 0,
    "forks_count": 9
  },
  {
    "full_name": "alexellis/kubetrim",
    "stargazers_count": 118,
    "open_issues_count": 5,
    "forks_count": 8
  },
  {
    "full_name": "exo-explore/exo",
    "stargazers_count": 28362,
    "open_issues_count": 406,
    "forks_count": 1785
  },
  {
    "full_name": "kubernetes/kubernetes",
    "stargazers_count": 115536,
    "open_issues_count": 2529,
    "forks_count": 40671
  },
  {
    "full_name": "scalacenter/scalafix",
    "stargazers_count": 851,
    "open_issues_count": 71,
    "forks_count": 187
  },
  {
    "full_name": "mschwager/fierce",
    "stargazers_count": 1694,
    "open_issues_count": 7,
    "forks_count": 211
  },
  {
    "full_name": "foyer-rs/foyer",
    "stargazers_count": 970,
    "open_issues_count": 67,
    "forks_count": 44
  },
  {
    "full_name": "starkware-libs/cairo",
    "stargazers_count": 1762,
    "open_issues_count": 129,
    "forks_count": 604
  },
  {
    "full_name": "rfjakob/earlyoom",
    "stargazers_count": 3406,
    "open_issues_count": 20,
    "forks_count": 177
  },
  {
    "full_name": "eza-community/eza",
    "stargazers_count": 15697,
    "open_issues_count": 252,
    "forks_count": 297
  },
  {
    "full_name": "ublue-os/fleek",
    "stargazers_count": 825,
    "open_issues_count": 70,
    "forks_count": 28
  },
  {
    "full_name": "cheat/cheat",
    "stargazers_count": 12820,
    "open_issues_count": 43,
    "forks_count": 831
  },
  {
    "full_name": "ajeetdsouza/zoxide",
    "stargazers_count": 26935,
    "open_issues_count": 122,
    "forks_count": 638
  },
  {
    "full_name": "amazon-science/chronos-forecasting",
    "stargazers_count": 3335,
    "open_issues_count": 20,
    "forks_count": 379
  },
  {
    "full_name": "francoismichel/ssh3",
    "stargazers_count": 3371,
    "open_issues_count": 56,
    "forks_count": 92
  },
  {
    "full_name": "conductor-oss/conductor",
    "stargazers_count": 23163,
    "open_issues_count": 81,
    "forks_count": 620
  },
  {
    "full_name": "zed-industries/zed",
    "stargazers_count": 61002,
    "open_issues_count": 2652,
    "forks_count": 4422
  }
]