[
  {
    "full_name": "zitadel/zitadel",
    "stargazers_count": 12038,
    "open_issues_count": 895,
    "forks_count": 845
  },
  {
    "full_name": "JanDeDobbeleer/oh-my-posh",
    "stargazers_count": 20421,
    "open_issues_count": 19,
    "forks_count": 2620
  },
  {
    "full_name": "dgraph-io/ristretto",
    "stargazers_count": 6537,
    "open_issues_count": 10,
    "forks_count": 425
  },
  {
    "full_name": "aws/aws-sdk-go-v2",
    "stargazers_count": 3320,
    "open_issues_count": 90,
    "forks_count": 727
  },
  {
    "full_name": "apple/container",
    "stargazers_count": 21718,
    "open_issues_count": 194,
    "forks_count": 499
  },
  {
    "full_name": "chonkie-inc/chonkie",
    "stargazers_count": 3058,
    "open_issues_count": 41,
    "forks_count": 196
  },
  {
    "full_name": "tindy2013/subconverter",
    "stargazers_count": 15230,
    "open_issues_count": 246,
    "forks_count": 3448
  },
  {
    "full_name": "zellij-org/zellij",
    "stargazers_count": 26908,
    "open_issues_count": 1366,
    "forks_count": 845
  },
  {
    "full_name": "go-resty/resty",
    "stargazers_count": 11313,
    "open_issues_count": 50,
    "forks_count": 772
  },
  {
    "full_name": "jd/tenacity",
    "stargazers_count": 7991,
    "open_issues_count": 128,
    "forks_count": 301
  },
  {
    "full_name": "litl/backoff",
    "stargazers_count": 2701,
    "open_issues_count": 66,
    "forks_count": 155
  },
  {
    "full_name": "grafana/k6",
    "stargazers_count": 29049,
    "open_issues_count": 756,
    "forks_count": 1434
  },
  {
    "full_name": "gohugoio/hugo",
    "stargazers_count": 84389,
    "open_issues_count": 393,
    "forks_count": 8082
  },
  {
    "full_name": "go-playground/validator",
    "stargazers_count": 19182,
    "open_issues_count": 321,
    "forks_count": 1387
  },
  {
    "full_name": "external-secrets/external-secrets",
    "stargazers_count": 5981,
    "open_issues_count": 205,
    "forks_count": 1108
  },
  {
    "full_name": "mermaid-js/mermaid",
    "stargazers_count": 83755,
    "open_issues_count": 1501,
    "forks_count": 8223
  },
  {
    "full_name": "libjpeg-turbo/libjpeg-turbo",
    "stargazers_count": 4089,
    "open_issues_count": 21,
    "forks_count": 1095
  },
  {
    "full_name": "valeriansaliou/sonic",
    "stargazers_count": 21017,
    "open_issues_count": 73,
    "forks_count": 605
  },
  {
    "full_name": "cvilsmeier/go-sqlite-bench",
    "stargazers_count": 547,
    "open_issues_count": 2,
    "forks_count": 9
  },
  {
    "full_name": "alexellis/kubetrim",
    "stargazers_count": 124,
    "open_issues_count": 6,
    "forks_count": 10
  },
  {
    "full_name": "exo-explore/exo",
    "stargazers_count": 32147,
    "open_issues_count": 447,
    "forks_count": 2172
  },
  {
    "full_name": "kubernetes/kubernetes",
    "stargazers_count": 118237,
    "open_issues_count": 2560,
    "forks_count": 41586
  },
  {
    "full_name": "scalacenter/scalafix",
    "stargazers_count": 863,
    "open_issues_count": 80,
    "forks_count": 188
  },
  {
    "full_name": "mschwager/fierce",
    "stargazers_count": 1730,
    "open_issues_count": 8,
    "forks_count": 213
  },
  {
    "full_name": "foyer-rs/foyer",
    "stargazers_count": 1464,
    "open_issues_count": 75,
    "forks_count": 62
  },
  {
    "full_name": "starkware-libs/cairo",
    "stargazers_count": 1812,
    "open_issues_count": 146,
    "forks_count": 638
  },
  {
    "full_name": "rfjakob/earlyoom",
    "stargazers_count": 3663,
    "open_issues_count": 23,
    "forks_count": 188
  },
  {
    "full_name": "eza-community/eza",
    "stargazers_count": 18141,
    "open_issues_count": 306,
    "forks_count": 339
  },
  {
    "full_name": "ublue-os/fleek",
    "stargazers_count": 821,
    "open_issues_count": 70,
    "forks_count": 28
  },
  {
    "full_name": "cheat/cheat",
    "stargazers_count": 13040,
    "open_issues_count": 49,
    "forks_count": 838
  }
]